License.txt
MANIFEST.in
Readme.txt
setup.py
oye_vix/__init__.py
oye_vix/my_cmd.py
oye_vix/vicky.py
oye_vix.egg-info/PKG-INFO
oye_vix.egg-info/SOURCES.txt
oye_vix.egg-info/dependency_links.txt
oye_vix.egg-info/top_level.txt